{
	"metadata": {
		"generatedAt": "2023-09-26T14:00:09.305Z"
	},
	"runtimeData": [
		{
			"runtime": "lambda-perf-nodejs16x-256-arm64",
			"displayName": "nodejs16.x",
			"initDurations": [
				150.71,
				179.97,
				160.03,
				170.26,
				156.67,
				164.17,
				157.01,
				158.08,
				167.79,
				155.43
			],
			"memorySize": 256,
			"architecture": "arm64",
			"averageMemoryUsed": 55.1,
			"averageDuration": 4.544,
			"averageColdStartDuration": 162.012
		},
		{
			"runtime": "lambda-perf-go_on_provided-1024-x86_64",
			"displayName": "go (provided)",
			"initDurations": [
				51.87,
				52.2,
				53.13,
				55.01,
				54.89,
				57.1,
				57.98,
				56.55,
				46.01,
				53.61
			],
			"memorySize": 1024,
			"architecture": "x86_64",
			"averageMemoryUsed": 19,
			"averageDuration": 1.6,
			"averageColdStartDuration": 53.835
		},
		{
			"runtime": "lambda-perf-python39-1024-arm64",
			"displayName": "python3.9",
			"initDurations": [
				114.85,
				107.99,
				107.82,
				108.06,
				109.12,
				105.17,
				114.03,
				112.97,
				99.12,
				108.6
			],
			"memorySize": 1024,
			"architecture": "arm64",
			"averageMemoryUsed": 35.1,
			"averageDuration": 1.572,
			"averageColdStartDuration": 108.773
		},
		{
			"runtime": "lambda-perf-python311-1024-arm64",
			"displayName": "python3.11",
			"initDurations": [
				106.65,
				117.29,
				107.28,
				113.36,
				106.64,
				99,
				149.12,
				100.79,
				105.35,
				105.1
			],
			"memorySize": 1024,
			"architecture": "arm64",
			"averageMemoryUsed": 41.6,
			"averageDuration": 2.37,
			"averageColdStartDuration": 111.058
		},
		{
			"runtime": "lambda-perf-java11-128-x86_64",
			"displayName": "java11",
			"initDurations": [
				290.67,
				247.69,
				266.2,
				273.98,
				250.24,
				261.35,
				253.11,
				259.4,
				256.45,
				219.68
			],
			"memorySize": 128,
			"architecture": "x86_64",
			"averageMemoryUsed": 69,
			"averageDuration": 10.902,
			"averageColdStartDuration": 257.877
		},
		{
			"runtime": "lambda-perf-cpp11-512-x86_64",
			"displayName": "c++ 11 (prov.al2)",
			"initDurations": [
				117.06,
				127.82,
				120.05,
				124.39,
				109.37,
				139.55,
				118.56,
				110.26,
				118.34,
				167.76
			],
			"memorySize": 512,
			"architecture": "x86_64",
			"averageMemoryUsed": 30.3,
			"averageDuration": 2.474,
			"averageColdStartDuration": 125.316
		},
		{
			"runtime": "lambda-perf-ruby27-512-arm64",
			"displayName": "ruby2.7",
			"initDurations": [
				167.89,
				156.21,
				162.56,
				153.9,
				148.29,
				160.23,
				148.2,
				152.62,
				159.19,
				171.28
			],
			"memorySize": 512,
			"architecture": "arm64",
			"averageMemoryUsed": 31,
			"averageDuration": 4.437,
			"averageColdStartDuration": 158.037
		},
		{
			"runtime": "lambda-perf-dotnet6-128-x86_64",
			"displayName": "dotnet6",
			"initDurations": [
				220.98,
				224.96,
				253.07,
				244.97,
				228.74,
				245.73,
				240.38,
				232.55,
				218.07,
				232.55
			],
			"memorySize": 128,
			"architecture": "x86_64",
			"averageMemoryUsed": 59.4,
			"averageDuration": 547.215,
			"averageColdStartDuration": 234.2
		},
		{
			"runtime": "lambda-perf-graalvm_java17_on_provided_al2-128-arm64",
			"displayName": "graalvm java17 (prov.al2)",
			"initDurations": [
				118.83,
				124.88,
				119.67,
				118.62,
				120.06,
				119.51,
				126.02,
				122.38,
				119.93,
				121.69
			],
			"memorySize": 128,
			"architecture": "arm64",
			"averageMemoryUsed": 33.1,
			"averageDuration": 88.406,
			"averageColdStartDuration": 121.159
		},
		{
			"runtime": "lambda-perf-bun-128-x86_64",
			"displayName": "bun (prov.al2)",
			"initDurations": [
				374.18,
				381.99,
				375.62,
				383.72,
				386.49,
				404.32,
				413.82,
				331.69,
				376.48,
				371.34
			],
			"memorySize": 128,
			"architecture": "x86_64",
			"averageMemoryUsed": 76,
			"averageDuration": 189.338,
			"averageColdStartDuration": 379.965
		},
		{
			"runtime": "lambda-perf-bun-1024-arm64",
			"displayName": "bun (prov.al2)",
			"initDurations": [
				328.48,
				342.24,
				326.65,
				327.93,
				323.36,
				335.35,
				331.93,
				326.32,
				325.79,
				331.74
			],
			"memorySize": 1024,
			"architecture": "arm64",
			"averageMemoryUsed": 72.1,
			"averageDuration": 12.939,
			"averageColdStartDuration": 329.979
		},
		{
			"runtime": "lambda-perf-nodejs14x-1024-x86_64",
			"displayName": "nodejs14.x",
			"initDurations": [
				197.21,
				203.06,
				174.31,
				186.63,
				159.47,
				175.71,
				196.06,
				170.95,
				203.81,
				167.39
			],
			"memorySize": 1024,
			"architecture": "x86_64",
			"averageMemoryUsed": 57,
			"averageDuration": 2.554,
			"averageColdStartDuration": 183.46
		},
		{
			"runtime": "lambda-perf-java17-256-arm64",
			"displayName": "java17",
			"initDurations": [
				220.85,
				206.71,
				235.28,
				226.44,
				220.46,
				232.19,
				225.37,
				242.73,
				226.53,
				237.31
			],
			"memorySize": 256,
			"architecture": "arm64",
			"averageMemoryUsed": 66,
			"averageDuration": 2.54,
			"averageColdStartDuration": 227.387
		},
		{
			"runtime": "lambda-perf-python39-256-x86_64",
			"displayName": "python3.9",
			"initDurations": [
				121.87,
				111.98,
				124.16,
				113.84,
				111.47,
				103.31,
				103.36,
				105.03,
				127.51,
				106.81
			],
			"memorySize": 256,
			"architecture": "x86_64",
			"averageMemoryUsed": 36,
			"averageDuration": 1.457,
			"averageColdStartDuration": 112.934
		},
		{
			"runtime": "lambda-perf-python310-256-x86_64",
			"displayName": "python3.10",
			"initDurations": [
				120.83,
				108.58,
				113.52,
				111.44,
				111.12,
				117.93,
				130.74,
				114.34,
				92.92,
				110.97
			],
			"memorySize": 256,
			"architecture": "x86_64",
			"averageMemoryUsed": 36,
			"averageDuration": 6.081,
			"averageColdStartDuration": 113.239
		},
		{
			"runtime": "lambda-perf-nodejs14x-256-x86_64",
			"displayName": "nodejs14.x",
			"initDurations": [
				142.69,
				157.32,
				180.09,
				180.49,
				170.17,
				186.8,
				171.78,
				164.12,
				181.07,
				172.06
			],
			"memorySize": 256,
			"architecture": "x86_64",
			"averageMemoryUsed": 56.9,
			"averageDuration": 2.528,
			"averageColdStartDuration": 170.659
		},
		{
			"runtime": "lambda-perf-python38-1024-arm64",
			"displayName": "python3.8",
			"initDurations": [
				121.75,
				118.54,
				122.38,
				119.74,
				120.97,
				128.55,
				115.8,
				118.67,
				134.72,
				118.16
			],
			"memorySize": 1024,
			"architecture": "arm64",
			"averageMemoryUsed": 38,
			"averageDuration": 1.87,
			"averageColdStartDuration": 121.928
		},
		{
			"runtime": "lambda-perf-java11_snapstart-1024-x86_64",
			"displayName": "java11 snapstart",
			"initDurations": [
				265.99,
				218.35,
				281.87,
				253.06,
				281.18,
				248.25,
				259.23,
				263.75,
				280.19,
				340.25
			],
			"memorySize": 1024,
			"architecture": "x86_64",
			"averageMemoryUsed": 68.7,
			"averageDuration": 3.434,
			"averageColdStartDuration": 269.212
		},
		{
			"runtime": "lambda-perf-go_on_provided-128-x86_64",
			"displayName": "go (provided)",
			"initDurations": [
				64.04,
				54.26,
				53.01,
				59.47,
				53.23,
				75.73,
				55.74,
				59.9,
				54.33,
				61.59
			],
			"memorySize": 128,
			"architecture": "x86_64",
			"averageMemoryUsed": 19,
			"averageDuration": 1.94,
			"averageColdStartDuration": 59.13
		},
		{
			"runtime": "lambda-perf-nodejs14x-512-arm64",
			"displayName": "nodejs14.x",
			"initDurations": [
				184.94,
				188.52,
				181.24,
				185.46,
				180.83,
				178.07,
				183.15,
				186.15,
				182.94,
				182.23
			],
			"memorySize": 512,
			"architecture": "arm64",
			"averageMemoryUsed": 56,
			"averageDuration": 3.501,
			"averageColdStartDuration": 183.353
		},
		{
			"runtime": "lambda-perf-ruby32-256-x86_64",
			"displayName": "ruby3.2",
			"initDurations": [
				187.41,
				200.09,
				235.56,
				181.46,
				188.63,
				190.4,
				204.38,
				187.33,
				186.96,
				207.76
			],
			"memorySize": 256,
			"architecture": "x86_64",
			"averageMemoryUsed": 36,
			"averageDuration": 3.109,
			"averageColdStartDuration": 196.998
		},
		{
			"runtime": "lambda-perf-go_on_provided_al2-512-x86_64",
			"displayName": "go (prov.al2)",
			"initDurations": [
				56.74,
				54.32,
				43.8,
				55.78,
				60.71,
				55.34,
				53.66,
				57.56,
				49.22,
				55.59
			],
			"memorySize": 512,
			"architecture": "x86_64",
			"averageMemoryUsed": 19.1,
			"averageDuration": 1.321,
			"averageColdStartDuration": 54.272
		},
		{
			"runtime": "lambda-perf-python38-512-x86_64",
			"displayName": "python3.8",
			"initDurations": [
				124.21,
				120.08,
				141.41,
				148.17,
				130.64,
				118.69,
				123.08,
				106,
				124.18,
				131.87
			],
			"memorySize": 512,
			"architecture": "x86_64",
			"averageMemoryUsed": 38.6,
			"averageDuration": 1.655,
			"averageColdStartDuration": 126.833
		},
		{
			"runtime": "lambda-perf-bun-256-arm64",
			"displayName": "bun (prov.al2)",
			"initDurations": [
				333.32,
				324.46,
				330.31,
				333.19,
				374.62,
				335.99,
				325.72,
				327.99,
				339.53,
				322.38
			],
			"memorySize": 256,
			"architecture": "arm64",
			"averageMemoryUsed": 69.9,
			"averageDuration": 85.437,
			"averageColdStartDuration": 334.751
		},
		{
			"runtime": "lambda-perf-java8_al2-512-x86_64",
			"displayName": "java8.al2",
			"initDurations": [
				244.62,
				228.19,
				234.74,
				228.98,
				229.42,
				268.94,
				236.94,
				230.73,
				230.02,
				262.07
			],
			"memorySize": 512,
			"architecture": "x86_64",
			"averageMemoryUsed": 57.1,
			"averageDuration": 5.58,
			"averageColdStartDuration": 239.465
		},
		{
			"runtime": "lambda-perf-python39-512-x86_64",
			"displayName": "python3.9",
			"initDurations": [
				114.27,
				111.74,
				145.52,
				96.31,
				97.89,
				114.24,
				133.08,
				146.19,
				115.68,
				111.63
			],
			"memorySize": 512,
			"architecture": "x86_64",
			"averageMemoryUsed": 36,
			"averageDuration": 1.882,
			"averageColdStartDuration": 118.655
		},
		{
			"runtime": "lambda-perf-python310-512-arm64",
			"displayName": "python3.10",
			"initDurations": [
				147.9,
				109.63,
				111.27,
				113.48,
				106.5,
				111.49,
				109.67,
				108.44,
				109,
				156.19
			],
			"memorySize": 512,
			"architecture": "arm64",
			"averageMemoryUsed": 37.8,
			"averageDuration": 2.251,
			"averageColdStartDuration": 118.357
		},
		{
			"runtime": "lambda-perf-java17-512-x86_64",
			"displayName": "java17",
			"initDurations": [
				195.29,
				206.75,
				168.12,
				206.83,
				229.69,
				699.25,
				193.4,
				226.57,
				179.13,
				199.36
			],
			"memorySize": 512,
			"architecture": "x86_64",
			"averageMemoryUsed": 67,
			"averageDuration": 2.404,
			"averageColdStartDuration": 250.439
		},
		{
			"runtime": "lambda-perf-python310-512-x86_64",
			"displayName": "python3.10",
			"initDurations": [
				98.99,
				148.84,
				170.55,
				117.34,
				114.07,
				118.84,
				118.2,
				216.57,
				108,
				110.98
			],
			"memorySize": 512,
			"architecture": "x86_64",
			"averageMemoryUsed": 36.1,
			"averageDuration": 1.727,
			"averageColdStartDuration": 132.238
		},
		{
			"runtime": "lambda-perf-go1x-128-x86_64",
			"displayName": "go1.x",
			"initDurations": [
				94.35,
				92.13,
				88.19,
				123.74,
				99.95,
				85.78,
				83.34,
				69.79,
				89,
				69.86
			],
			"memorySize": 128,
			"architecture": "x86_64",
			"averageMemoryUsed": 29.1,
			"averageDuration": 4.481,
			"averageColdStartDuration": 89.613
		},
		{
			"runtime": "lambda-perf-python310-1024-arm64",
			"displayName": "python3.10",
			"initDurations": [
				108.31,
				108.11,
				143.93,
				109.71,
				112.66,
				111.32,
				150.04,
				108.53,
				112.43,
				107.1
			],
			"memorySize": 1024,
			"architecture": "arm64",
			"averageMemoryUsed": 38.1,
			"averageDuration": 2.518,
			"averageColdStartDuration": 117.214
		},
		{
			"runtime": "lambda-perf-nodejs16x-512-x86_64",
			"displayName": "nodejs16.x",
			"initDurations": [
				154.35,
				176.16,
				149.22,
				150.86,
				165.5,
				150.21,
				147.03,
				153.29,
				156.4,
				167.37
			],
			"memorySize": 512,
			"architecture": "x86_64",
			"averageMemoryUsed": 57.3,
			"averageDuration": 3.514,
			"averageColdStartDuration": 157.039
		},
		{
			"runtime": "lambda-perf-python311-128-arm64",
			"displayName": "python3.11",
			"initDurations": [
				102.16,
				112.17,
				108.32,
				113.6,
				102.03,
				118.09,
				110.06,
				109.56,
				105.7,
				107.97
			],
			"memorySize": 128,
			"architecture": "arm64",
			"averageMemoryUsed": 39,
			"averageDuration": 1.701,
			"averageColdStartDuration": 108.966
		},
		{
			"runtime": "lambda-perf-nodejs18x-1024-x86_64",
			"displayName": "nodejs18.x",
			"initDurations": [
				167.19,
				177.27,
				177.9,
				176.42,
				170.54,
				167.26,
				131.26,
				177.15,
				167.41,
				157.45
			],
			"memorySize": 1024,
			"architecture": "x86_64",
			"averageMemoryUsed": 67,
			"averageDuration": 2.689,
			"averageColdStartDuration": 166.985
		},
		{
			"runtime": "lambda-perf-ruby27-128-arm64",
			"displayName": "ruby2.7",
			"initDurations": [
				161.45,
				158.13,
				153.34,
				155.78,
				156.36,
				158.07,
				164.1,
				162.93,
				157.86,
				159.19
			],
			"memorySize": 128,
			"architecture": "arm64",
			"averageMemoryUsed": 31,
			"averageDuration": 36.218,
			"averageColdStartDuration": 158.721
		},
		{
			"runtime": "lambda-perf-python39-128-x86_64",
			"displayName": "python3.9",
			"initDurations": [
				98.49,
				107.71,
				103.7,
				106.22,
				114.51,
				109.76,
				109.09,
				124.15,
				110.2,
				117.17
			],
			"memorySize": 128,
			"architecture": "x86_64",
			"averageMemoryUsed": 36,
			"averageDuration": 2.063,
			"averageColdStartDuration": 110.1
		},
		{
			"runtime": "lambda-perf-dotnet7_aot_on_provided_al2-512-x86_64",
			"displayName": "dotnet7 aot (prov.al2)",
			"initDurations": [
				116.92,
				121.44,
				119.41,
				117.19,
				127.03,
				134.16,
				145.94,
				114.74,
				105.85,
				124.75
			],
			"memorySize": 512,
			"architecture": "x86_64",
			"averageMemoryUsed": 34,
			"averageDuration": 14.738,
			"averageColdStartDuration": 122.743
		},
		{
			"runtime": "lambda-perf-go_on_provided_al2-1024-arm64",
			"displayName": "go (prov.al2)",
			"initDurations": [
				47.47,
				48.43,
				48.63,
				47.06,
				47.43,
				56.16,
				49.95,
				49.29,
				49.54,
				48.95
			],
			"memorySize": 1024,
			"architecture": "arm64",
			"averageMemoryUsed": 19,
			"averageDuration": 1.594,
			"averageColdStartDuration": 49.291
		},
		{
			"runtime": "lambda-perf-python38-256-x86_64",
			"displayName": "python3.8",
			"initDurations": [
				122.97,
				118.13,
				115.16,
				127.24,
				139.91,
				128.07,
				159.12,
				193.08,
				121.22,
				144.93
			],
			"memorySize": 256,
			"architecture": "x86_64",
			"averageMemoryUsed": 38.5,
			"averageDuration": 1.718,
			"averageColdStartDuration": 136.983
		},
		{
			"runtime": "lambda-perf-java11-256-arm64",
			"displayName": "java11",
			"initDurations": [
				257.91,
				259.99,
				263.8,
				257.26,
				267.27,
				293.3,
				264.6,
				255.84,
				261.66,
				255.5
			],
			"memorySize": 256,
			"architecture": "arm64",
			"averageMemoryUsed": 66,
			"averageDuration": 3.414,
			"averageColdStartDuration": 263.713
		},
		{
			"runtime": "lambda-perf-java17-128-arm64",
			"displayName": "java17",
			"initDurations": [
				218.61,
				211.01,
				239.46,
				222.89,
				218.26,
				225.13,
				219.01,
				224.67,
				224,
				256.43
			],
			"memorySize": 128,
			"architecture": "arm64",
			"averageMemoryUsed": 66,
			"averageDuration": 12.553,
			"averageColdStartDuration": 225.947
		},
		{
			"runtime": "lambda-perf-java8-1024-x86_64",
			"displayName": "java8",
			"initDurations": [
				270.56,
				223.99,
				233.44,
				222.66,
				251.55,
				282.42,
				213.61,
				183.99,
				251.35,
				228.11
			],
			"memorySize": 1024,
			"architecture": "x86_64",
			"averageMemoryUsed": 57,
			"averageDuration": 5.327,
			"averageColdStartDuration": 236.168
		},
		{
			"runtime": "lambda-perf-swift58-128-x86_64",
			"displayName": "apple swift 5.8 (prov.al2)",
			"initDurations": [
				118.66,
				184.75,
				132.88,
				128.55,
				137.18,
				124.66,
				129.01,
				13.05,
				129.36,
				125.7
			],
			"memorySize": 128,
			"architecture": "x86_64",
			"averageMemoryUsed": 30.2,
			"averageDuration": 1.278,
			"averageColdStartDuration": 122.38
		},
		{
			"runtime": "lambda-perf-nodejs14x-128-arm64",
			"displayName": "nodejs14.x",
			"initDurations": [
				174.67,
				177.02,
				182.84,
				181.48,
				195.19,
				176.04,
				183.22,
				185.47,
				176.22,
				179.57
			],
			"memorySize": 128,
			"architecture": "arm64",
			"averageMemoryUsed": 56,
			"averageDuration": 14.621,
			"averageColdStartDuration": 181.172
		},
		{
			"runtime": "lambda-perf-java17_snapstart-1024-x86_64",
			"displayName": "java17 snapstart",
			"initDurations": [
				196.27,
				213.52,
				252.25,
				208.2,
				212.12,
				227.02,
				224.73,
				211.45,
				196.84,
				220.64
			],
			"memorySize": 1024,
			"architecture": "x86_64",
			"averageMemoryUsed": 67,
			"averageDuration": 3.456,
			"averageColdStartDuration": 216.304
		},
		{
			"runtime": "lambda-perf-go_on_provided_al2-512-arm64",
			"displayName": "go (prov.al2)",
			"initDurations": [
				48.69,
				48.44,
				47.8,
				48.73,
				49.8,
				48.47,
				48.37,
				46.86,
				49.24,
				51.97
			],
			"memorySize": 512,
			"architecture": "arm64",
			"averageMemoryUsed": 18.7,
			"averageDuration": 1.571,
			"averageColdStartDuration": 48.837
		},
		{
			"runtime": "lambda-perf-bun-512-arm64",
			"displayName": "bun (prov.al2)",
			"initDurations": [
				334.93,
				326.51,
				358.27,
				327.71,
				324.39,
				327.82,
				324.59,
				329.88,
				331.91,
				332.39
			],
			"memorySize": 512,
			"architecture": "arm64",
			"averageMemoryUsed": 72,
			"averageDuration": 26.178,
			"averageColdStartDuration": 331.84
		},
		{
			"runtime": "lambda-perf-rust_on_provided_al2-1024-arm64",
			"displayName": "rust (prov.al2)",
			"initDurations": [
				14.39,
				15.23,
				14.5,
				14.32,
				15.19,
				14.08,
				14.9,
				16.17,
				14.31,
				14.24
			],
			"memorySize": 1024,
			"architecture": "arm64",
			"averageMemoryUsed": 13.9,
			"averageDuration": 1.58,
			"averageColdStartDuration": 14.733
		},
		{
			"runtime": "lambda-perf-python38-128-x86_64",
			"displayName": "python3.8",
			"initDurations": [
				107.13,
				126.34,
				120.43,
				124.71,
				134.39,
				152.3,
				116.7,
				131.12,
				116.86,
				136.98
			],
			"memorySize": 128,
			"architecture": "x86_64",
			"averageMemoryUsed": 38.3,
			"averageDuration": 2.199,
			"averageColdStartDuration": 126.696
		},
		{
			"runtime": "lambda-perf-java8-128-x86_64",
			"displayName": "java8",
			"initDurations": [
				225.1,
				224.22,
				279.34,
				231.05,
				225.67,
				219.76,
				217.53,
				228.78,
				212.89,
				208.81
			],
			"memorySize": 128,
			"architecture": "x86_64",
			"averageMemoryUsed": 56.6,
			"averageDuration": 37.271,
			"averageColdStartDuration": 227.315
		},
		{
			"runtime": "lambda-perf-rust_on_provided_al2-256-x86_64",
			"displayName": "rust (prov.al2)",
			"initDurations": [
				20.5,
				15.92,
				15.39,
				17.41,
				15.46,
				15.54,
				18.93,
				19.12,
				17.29,
				15.84
			],
			"memorySize": 256,
			"architecture": "x86_64",
			"averageMemoryUsed": 14.1,
			"averageDuration": 3.202,
			"averageColdStartDuration": 17.14
		},
		{
			"runtime": "lambda-perf-java11-1024-x86_64",
			"displayName": "java11",
			"initDurations": [
				258.77,
				258.63,
				259.98,
				291.98,
				274.15,
				279.26,
				290.8,
				276.13,
				258.99,
				247.12
			],
			"memorySize": 1024,
			"architecture": "x86_64",
			"averageMemoryUsed": 68.9,
			"averageDuration": 3.43,
			"averageColdStartDuration": 269.581
		},
		{
			"runtime": "lambda-perf-swift58-512-x86_64",
			"displayName": "apple swift 5.8 (prov.al2)",
			"initDurations": [
				124.19,
				139.01,
				119.69,
				120.9,
				128.1,
				111.76,
				128.49,
				127.33,
				125.5,
				124.52
			],
			"memorySize": 512,
			"architecture": "x86_64",
			"averageMemoryUsed": 31.9,
			"averageDuration": 1.366,
			"averageColdStartDuration": 124.949
		},
		{
			"runtime": "lambda-perf-java17_snapstart-256-x86_64",
			"displayName": "java17 snapstart",
			"initDurations": [
				230.96,
				222.93,
				167.61,
				218.56,
				217.28,
				217.28,
				211.86,
				225.03,
				214.97,
				219.6
			],
			"memorySize": 256,
			"architecture": "x86_64",
			"averageMemoryUsed": 67.4,
			"averageDuration": 2.641,
			"averageColdStartDuration": 214.608
		},
		{
			"runtime": "lambda-perf-python311-512-arm64",
			"displayName": "python3.11",
			"initDurations": [
				105.35,
				157.65,
				110.9,
				103.87,
				108.46,
				103.61,
				109.53,
				95.73,
				152.22,
				111.17
			],
			"memorySize": 512,
			"architecture": "arm64",
			"averageMemoryUsed": 41.4,
			"averageDuration": 2.424,
			"averageColdStartDuration": 115.849
		},
		{
			"runtime": "lambda-perf-ruby27-1024-arm64",
			"displayName": "ruby2.7",
			"initDurations": [
				161.64,
				169.74,
				151.05,
				166.07,
				156.11,
				155.28,
				157.55,
				150.38,
				163.8,
				164.65
			],
			"memorySize": 1024,
			"architecture": "arm64",
			"averageMemoryUsed": 31,
			"averageDuration": 4.664,
			"averageColdStartDuration": 159.627
		},
		{
			"runtime": "lambda-perf-nodejs14x-128-x86_64",
			"displayName": "nodejs14.x",
			"initDurations": [
				180.94,
				173.38,
				174.84,
				165.78,
				187.78,
				179.35,
				181.44,
				170.13,
				170.83,
				178.5
			],
			"memorySize": 128,
			"architecture": "x86_64",
			"averageMemoryUsed": 57,
			"averageDuration": 16.982,
			"averageColdStartDuration": 176.297
		},
		{
			"runtime": "lambda-perf-nodejs18x-128-arm64",
			"displayName": "nodejs18.x",
			"initDurations": [
				183.72,
				174.83,
				184.41,
				169.73,
				189.03,
				180.21,
				173.33,
				175.33,
				181.05,
				164.09
			],
			"memorySize": 128,
			"architecture": "arm64",
			"averageMemoryUsed": 65.5,
			"averageDuration": 11.075,
			"averageColdStartDuration": 177.573
		},
		{
			"runtime": "lambda-perf-java8_al2-512-arm64",
			"displayName": "java8.al2",
			"initDurations": [
				246.34,
				234.58,
				254.15,
				253.23,
				259.14,
				237.07,
				251.09,
				243.56,
				238.83,
				235.6
			],
			"memorySize": 512,
			"architecture": "arm64",
			"averageMemoryUsed": 55,
			"averageDuration": 8.679,
			"averageColdStartDuration": 245.359
		},
		{
			"runtime": "lambda-perf-nodejs16x-128-arm64",
			"displayName": "nodejs16.x",
			"initDurations": [
				161.19,
				162.47,
				156.64,
				157.48,
				158.3,
				159.26,
				162.47,
				157.78,
				163.37,
				194.74
			],
			"memorySize": 128,
			"architecture": "arm64",
			"averageMemoryUsed": 55,
			"averageDuration": 11.317,
			"averageColdStartDuration": 163.37
		},
		{
			"runtime": "lambda-perf-dotnet7_aot_on_provided_al2-1024-arm64",
			"displayName": "dotnet7 aot (prov.al2)",
			"initDurations": [
				144.06,
				158.43,
				145.99,
				144.6,
				145.12,
				143.92,
				147.42,
				147.77,
				146.56,
				142.14
			],
			"memorySize": 1024,
			"architecture": "arm64",
			"averageMemoryUsed": 41.1,
			"averageDuration": 40.955,
			"averageColdStartDuration": 146.601
		},
		{
			"runtime": "lambda-perf-python38-512-arm64",
			"displayName": "python3.8",
			"initDurations": [
				120.98,
				125.71,
				116.04,
				120.68,
				119.86,
				113.49,
				118.58,
				121.65,
				130.44,
				124.4
			],
			"memorySize": 512,
			"architecture": "arm64",
			"averageMemoryUsed": 38,
			"averageDuration": 1.811,
			"averageColdStartDuration": 121.183
		},
		{
			"runtime": "lambda-perf-graalvm_java17_on_provided_al2-128-x86_64",
			"displayName": "graalvm java17 (prov.al2)",
			"initDurations": [
				129.22,
				127.23,
				134.81,
				136.48,
				133.94,
				146.18,
				127.93,
				133.85,
				151.04,
				134.71
			],
			"memorySize": 128,
			"architecture": "x86_64",
			"averageMemoryUsed": 34,
			"averageDuration": 88.576,
			"averageColdStartDuration": 135.539
		},
		{
			"runtime": "lambda-perf-java17-1024-arm64",
			"displayName": "java17",
			"initDurations": [
				255.46,
				221.65,
				218.92,
				215.14,
				221.1,
				224.28,
				227.68,
				222.72,
				212.86,
				238.68
			],
			"memorySize": 1024,
			"architecture": "arm64",
			"averageMemoryUsed": 66,
			"averageDuration": 2.807,
			"averageColdStartDuration": 225.849
		},
		{
			"runtime": "lambda-perf-go_on_provided-256-x86_64",
			"displayName": "go (provided)",
			"initDurations": [
				55.74,
				53.09,
				54.69,
				63.17,
				55.47,
				45.91,
				56.62,
				52.77,
				53.46,
				58.23
			],
			"memorySize": 256,
			"architecture": "x86_64",
			"averageMemoryUsed": 19,
			"averageDuration": 3.406,
			"averageColdStartDuration": 54.915
		},
		{
			"runtime": "lambda-perf-java11-512-arm64",
			"displayName": "java11",
			"initDurations": [
				260.63,
				250.27,
				259.95,
				258.01,
				249.76,
				235.16,
				253.22,
				261.01,
				256.12,
				264.97
			],
			"memorySize": 512,
			"architecture": "arm64",
			"averageMemoryUsed": 65.1,
			"averageDuration": 3.232,
			"averageColdStartDuration": 254.91
		},
		{
			"runtime": "lambda-perf-rust_on_provided_al2-128-arm64",
			"displayName": "rust (prov.al2)",
			"initDurations": [
				14.06,
				14.44,
				14.89,
				14.35,
				13.94,
				14.61,
				14.5,
				14.67,
				14.55,
				15.35
			],
			"memorySize": 128,
			"architecture": "arm64",
			"averageMemoryUsed": 14,
			"averageDuration": 1.523,
			"averageColdStartDuration": 14.536
		},
		{
			"runtime": "lambda-perf-java11_snapstart-512-x86_64",
			"displayName": "java11 snapstart",
			"initDurations": [
				264.25,
				242.01,
				277.31,
				280.22,
				250.93,
				255.48,
				296.8,
				265.08,
				266.39,
				247.43
			],
			"memorySize": 512,
			"architecture": "x86_64",
			"averageMemoryUsed": 68.8,
			"averageDuration": 2.87,
			"averageColdStartDuration": 264.59
		},
		{
			"runtime": "lambda-perf-quarkus_native_on_provided_al2-512-x86_64",
			"displayName": "quarkus (prov.al2)",
			"initDurations": [
				261.5,
				264.12,
				253.82,
				260.64,
				248.15,
				270.71,
				264.61,
				262.87,
				254.69,
				252.83
			],
			"memorySize": 512,
			"architecture": "x86_64",
			"averageMemoryUsed": 57.4,
			"averageDuration": 43.758,
			"averageColdStartDuration": 259.394
		},
		{
			"runtime": "lambda-perf-rust_on_provided_al2-1024-x86_64",
			"displayName": "rust (prov.al2)",
			"initDurations": [
				14.53,
				16.47,
				16.32,
				16.77,
				19.04,
				18.7,
				15.38,
				17.31,
				15.61,
				21.47
			],
			"memorySize": 1024,
			"architecture": "x86_64",
			"averageMemoryUsed": 14,
			"averageDuration": 1.217,
			"averageColdStartDuration": 17.16
		},
		{
			"runtime": "lambda-perf-bun-512-x86_64",
			"displayName": "bun (prov.al2)",
			"initDurations": [
				418.02,
				382.64,
				415.12,
				327.49,
				388.28,
				391.62,
				383.95,
				433.82,
				493.2,
				418.09
			],
			"memorySize": 512,
			"architecture": "x86_64",
			"averageMemoryUsed": 78.1,
			"averageDuration": 32.103,
			"averageColdStartDuration": 405.223
		},
		{
			"runtime": "lambda-perf-swift58-256-x86_64",
			"displayName": "apple swift 5.8 (prov.al2)",
			"initDurations": [
				132.4,
				130.4,
				119.5,
				172.19,
				148.44,
				170.14,
				139.5,
				134.83,
				117.9,
				144.28
			],
			"memorySize": 256,
			"architecture": "x86_64",
			"averageMemoryUsed": 32,
			"averageDuration": 3.181,
			"averageColdStartDuration": 140.958
		},
		{
			"runtime": "lambda-perf-python37-512-x86_64",
			"displayName": "python3.7",
			"initDurations": [
				128.87,
				113.47,
				142.78,
				117.19,
				106.57,
				147.73,
				117.09,
				136.56,
				112.62,
				124.79
			],
			"memorySize": 512,
			"architecture": "x86_64",
			"averageMemoryUsed": 36,
			"averageDuration": 2.987,
			"averageColdStartDuration": 124.767
		},
		{
			"runtime": "lambda-perf-python39-1024-x86_64",
			"displayName": "python3.9",
			"initDurations": [
				121.2,
				103.02,
				113.58,
				118.98,
				128.66,
				122.74,
				113.6,
				113.79,
				111.32,
				109.18
			],
			"memorySize": 1024,
			"architecture": "x86_64",
			"averageMemoryUsed": 36,
			"averageDuration": 3.509,
			"averageColdStartDuration": 115.607
		},
		{
			"runtime": "lambda-perf-python310-128-x86_64",
			"displayName": "python3.10",
			"initDurations": [
				113.25,
				119.61,
				107.93,
				100.36,
				113.55,
				116.64,
				113.39,
				149.69,
				125.82,
				161.57
			],
			"memorySize": 128,
			"architecture": "x86_64",
			"averageMemoryUsed": 36.1,
			"averageDuration": 1.881,
			"averageColdStartDuration": 122.181
		},
		{
			"runtime": "lambda-perf-cpp11-256-arm64",
			"displayName": "c++ 11 (prov.al2)",
			"initDurations": [
				99.17,
				92.84,
				95.98,
				93.87,
				99.49,
				101.99,
				98.43,
				98.26,
				98.02,
				100.05
			],
			"memorySize": 256,
			"architecture": "arm64",
			"averageMemoryUsed": 28.5,
			"averageDuration": 1.306,
			"averageColdStartDuration": 97.81
		},
		{
			"runtime": "lambda-perf-nodejs16x-1024-arm64",
			"displayName": "nodejs16.x",
			"initDurations": [
				157.12,
				158.89,
				160.69,
				159.33,
				159.68,
				158.34,
				155.25,
				159.34,
				156.92,
				173.44
			],
			"memorySize": 1024,
			"architecture": "arm64",
			"averageMemoryUsed": 55,
			"averageDuration": 3.142,
			"averageColdStartDuration": 159.9
		},
		{
			"runtime": "lambda-perf-python38-128-arm64",
			"displayName": "python3.8",
			"initDurations": [
				119.2,
				115,
				118.53,
				119.02,
				120.53,
				123.21,
				121.08,
				118.22,
				127.57,
				116.73
			],
			"memorySize": 128,
			"architecture": "arm64",
			"averageMemoryUsed": 38,
			"averageDuration": 3.107,
			"averageColdStartDuration": 119.909
		},
		{
			"runtime": "lambda-perf-quarkus_native_on_provided_al2-1024-x86_64",
			"displayName": "quarkus (prov.al2)",
			"initDurations": [
				256.98,
				248.94,
				269.46,
				261.84,
				225.99,
				273.64,
				19.51,
				267,
				234.41,
				320.83
			],
			"memorySize": 1024,
			"architecture": "x86_64",
			"averageMemoryUsed": 53.5,
			"averageDuration": 19.703,
			"averageColdStartDuration": 237.86
		},
		{
			"runtime": "lambda-perf-ruby27-256-x86_64",
			"displayName": "ruby2.7",
			"initDurations": [
				211.3,
				164.52,
				155.84,
				167.07,
				180.96,
				153.26,
				154.54,
				185.1,
				221.17,
				156.48
			],
			"memorySize": 256,
			"architecture": "x86_64",
			"averageMemoryUsed": 30.8,
			"averageDuration": 9.411,
			"averageColdStartDuration": 175.024
		},
		{
			"runtime": "lambda-perf-java11_snapstart-256-x86_64",
			"displayName": "java11 snapstart",
			"initDurations": [
				228.48,
				253.76,
				254.46,
				262.48,
				263.75,
				248.5,
				257.17,
				263.06,
				252.96,
				277.94
			],
			"memorySize": 256,
			"architecture": "x86_64",
			"averageMemoryUsed": 69.1,
			"averageDuration": 4.315,
			"averageColdStartDuration": 256.256
		},
		{
			"runtime": "lambda-perf-python38-256-arm64",
			"displayName": "python3.8",
			"initDurations": [
				118.76,
				121.42,
				123.46,
				118.75,
				116.17,
				127.64,
				114.23,
				127.74,
				118.87,
				116.07
			],
			"memorySize": 256,
			"architecture": "arm64",
			"averageMemoryUsed": 38,
			"averageDuration": 1.684,
			"averageColdStartDuration": 120.311
		},
		{
			"runtime": "lambda-perf-go1x-256-x86_64",
			"displayName": "go1.x",
			"initDurations": [
				86.45,
				87.54,
				89.39,
				87.8,
				93.02,
				89.39,
				131.82,
				81.51,
				70.03,
				106.14
			],
			"memorySize": 256,
			"architecture": "x86_64",
			"averageMemoryUsed": 29.1,
			"averageDuration": 2.677,
			"averageColdStartDuration": 92.309
		},
		{
			"runtime": "lambda-perf-swift58-1024-arm64",
			"displayName": "apple swift 5.8 (prov.al2)",
			"initDurations": [
				110.57,
				115.34,
				110.49,
				107.89,
				115.75,
				109.18,
				111.67,
				109.07,
				106.07,
				112.69
			],
			"memorySize": 1024,
			"architecture": "arm64",
			"averageMemoryUsed": 31,
			"averageDuration": 1.556,
			"averageColdStartDuration": 110.872
		},
		{
			"runtime": "lambda-perf-java8_al2-128-x86_64",
			"displayName": "java8.al2",
			"initDurations": [
				271.46,
				228.29,
				259.08,
				224.93,
				226.51,
				235.25,
				224.84,
				226.45,
				229.09,
				249.47
			],
			"memorySize": 128,
			"architecture": "x86_64",
			"averageMemoryUsed": 56,
			"averageDuration": 64.319,
			"averageColdStartDuration": 237.537
		},
		{
			"runtime": "lambda-perf-java11_snapstart-128-x86_64",
			"displayName": "java11 snapstart",
			"initDurations": [
				276.51,
				262.75,
				265.27,
				255.21,
				295.42,
				270.79,
				257.4,
				256.97,
				254.23,
				223.85
			],
			"memorySize": 128,
			"architecture": "x86_64",
			"averageMemoryUsed": 69,
			"averageDuration": 8.917,
			"averageColdStartDuration": 261.84
		},
		{
			"runtime": "lambda-perf-python311-256-x86_64",
			"displayName": "python3.11",
			"initDurations": [
				119.02,
				145.4,
				167.59,
				130.95,
				115.61,
				126.56,
				112.48,
				515.36,
				120.16,
				114.58
			],
			"memorySize": 256,
			"architecture": "x86_64",
			"averageMemoryUsed": 40,
			"averageDuration": 1.752,
			"averageColdStartDuration": 166.771
		},
		{
			"runtime": "lambda-perf-dotnet7_aot_on_provided_al2-256-x86_64",
			"displayName": "dotnet7 aot (prov.al2)",
			"initDurations": [
				119.11,
				112.86,
				102.06,
				130.77,
				124.23,
				134.05,
				108.11,
				136.85,
				116.41,
				115.91
			],
			"memorySize": 256,
			"architecture": "x86_64",
			"averageMemoryUsed": 34,
			"averageDuration": 13.558,
			"averageColdStartDuration": 120.036
		},
		{
			"runtime": "lambda-perf-dotnet7_aot_on_provided_al2-128-arm64",
			"displayName": "dotnet7 aot (prov.al2)",
			"initDurations": [
				153.77,
				149.02,
				154.38,
				146.32,
				141.98,
				148.21,
				147.08,
				155.26,
				144.67,
				143.66
			],
			"memorySize": 128,
			"architecture": "arm64",
			"averageMemoryUsed": 41,
			"averageDuration": 395.574,
			"averageColdStartDuration": 148.435
		},
		{
			"runtime": "lambda-perf-bun-1024-x86_64",
			"displayName": "bun (prov.al2)",
			"initDurations": [
				399,
				400.56,
				369.07,
				435.1,
				385.95,
				389.32,
				392.38,
				415.69,
				376.71,
				394.02
			],
			"memorySize": 1024,
			"architecture": "x86_64",
			"averageMemoryUsed": 78.4,
			"averageDuration": 12.27,
			"averageColdStartDuration": 395.78
		},
		{
			"runtime": "lambda-perf-bun_layer-512-x86_64",
			"displayName": "bun layer(prov.al2)",
			"initDurations": [
				480.55,
				489.29,
				830.71,
				491.49,
				500.53,
				409.94,
				508.41,
				499.25,
				793.36,
				654.35
			],
			"memorySize": 512,
			"architecture": "x86_64",
			"averageMemoryUsed": 93.1,
			"averageDuration": 10.396,
			"averageColdStartDuration": 565.788
		},
		{
			"runtime": "lambda-perf-ruby27-512-x86_64",
			"displayName": "ruby2.7",
			"initDurations": [
				147.45,
				140.57,
				149.1,
				150.45,
				169.97,
				144.78,
				114.11,
				191.39,
				187.02,
				153.87
			],
			"memorySize": 512,
			"architecture": "x86_64",
			"averageMemoryUsed": 31,
			"averageDuration": 4.206,
			"averageColdStartDuration": 154.871
		},
		{
			"runtime": "lambda-perf-python310-1024-x86_64",
			"displayName": "python3.10",
			"initDurations": [
				126.86,
				122.56,
				124.09,
				162.48,
				108.03,
				174.91,
				111.26,
				113.9,
				120.99,
				121.41
			],
			"memorySize": 1024,
			"architecture": "x86_64",
			"averageMemoryUsed": 36,
			"averageDuration": 3.032,
			"averageColdStartDuration": 128.649
		},
		{
			"runtime": "lambda-perf-swift58-512-arm64",
			"displayName": "apple swift 5.8 (prov.al2)",
			"initDurations": [
				116.73,
				111.83,
				114.21,
				108.49,
				110.82,
				112.13,
				114.11,
				108.55,
				115.17,
				111.55
			],
			"memorySize": 512,
			"architecture": "arm64",
			"averageMemoryUsed": 31,
			"averageDuration": 1.576,
			"averageColdStartDuration": 112.359
		},
		{
			"runtime": "lambda-perf-nodejs18x-1024-arm64",
			"displayName": "nodejs18.x",
			"initDurations": [
				177.72,
				182.51,
				187.51,
				181.72,
				180.84,
				171.12,
				179.78,
				173.97,
				201.26,
				170.55
			],
			"memorySize": 1024,
			"architecture": "arm64",
			"averageMemoryUsed": 70.1,
			"averageDuration": 3.794,
			"averageColdStartDuration": 180.698
		},
		{
			"runtime": "lambda-perf-graalvm_java17_on_provided_al2-512-x86_64",
			"displayName": "graalvm java17 (prov.al2)",
			"initDurations": [
				134.72,
				132.57,
				127.1,
				172.71,
				129.22,
				132.21,
				138.73,
				127.94,
				140.02,
				135.49
			],
			"memorySize": 512,
			"architecture": "x86_64",
			"averageMemoryUsed": 34,
			"averageDuration": 14.225,
			"averageColdStartDuration": 137.071
		},
		{
			"runtime": "lambda-perf-dotnet6-256-x86_64",
			"displayName": "dotnet6",
			"initDurations": [
				249.37,
				224.82,
				226.78,
				221.23,
				217.08,
				251.13,
				246.22,
				222.1,
				228.7,
				231.75
			],
			"memorySize": 256,
			"architecture": "x86_64",
			"averageMemoryUsed": 59.6,
			"averageDuration": 279.204,
			"averageColdStartDuration": 231.918
		},
		{
			"runtime": "lambda-perf-bun_layer-256-x86_64",
			"displayName": "bun layer(prov.al2)",
			"initDurations": [
				502.46,
				581.77,
				421.29,
				543.93,
				483.56,
				482.85,
				480.74,
				505.76,
				504.81,
				469.2
			],
			"memorySize": 256,
			"architecture": "x86_64",
			"averageMemoryUsed": 91.2,
			"averageDuration": 35.749,
			"averageColdStartDuration": 497.637
		},
		{
			"runtime": "lambda-perf-nodejs18x-512-arm64",
			"displayName": "nodejs18.x",
			"initDurations": [
				179.78,
				173.16,
				172.86,
				181.17,
				177.91,
				169.02,
				171.76,
				175.43,
				167.23,
				170.19
			],
			"memorySize": 512,
			"architecture": "arm64",
			"averageMemoryUsed": 70.2,
			"averageDuration": 3.906,
			"averageColdStartDuration": 173.851
		},
		{
			"runtime": "lambda-perf-cpp11-128-x86_64",
			"displayName": "c++ 11 (prov.al2)",
			"initDurations": [
				123.28,
				120.56,
				123.05,
				117.48,
				116.58,
				116.37,
				135.13,
				118.61,
				122.58,
				131.2
			],
			"memorySize": 128,
			"architecture": "x86_64",
			"averageMemoryUsed": 30.3,
			"averageDuration": 1.367,
			"averageColdStartDuration": 122.484
		},
		{
			"runtime": "lambda-perf-java8_al2-1024-arm64",
			"displayName": "java8.al2",
			"initDurations": [
				233.86,
				249.77,
				237.64,
				255.41,
				239.72,
				224.84,
				240.14,
				241.4,
				242.9,
				241.07
			],
			"memorySize": 1024,
			"architecture": "arm64",
			"averageMemoryUsed": 55.1,
			"averageDuration": 5.25,
			"averageColdStartDuration": 240.675
		},
		{
			"runtime": "lambda-perf-nodejs18x-256-x86_64",
			"displayName": "nodejs18.x",
			"initDurations": [
				190.8,
				155.18,
				167.88,
				170.42,
				216.9,
				181.79,
				170.06,
				161.39,
				170.95,
				180.62
			],
			"memorySize": 256,
			"architecture": "x86_64",
			"averageMemoryUsed": 67,
			"averageDuration": 3.955,
			"averageColdStartDuration": 176.599
		},
		{
			"runtime": "lambda-perf-go_on_provided_al2-256-x86_64",
			"displayName": "go (prov.al2)",
			"initDurations": [
				55.37,
				57.15,
				58.51,
				61.81,
				59.92,
				56.65,
				55.09,
				55,
				53.1,
				68.69
			],
			"memorySize": 256,
			"architecture": "x86_64",
			"averageMemoryUsed": 19.3,
			"averageDuration": 1.438,
			"averageColdStartDuration": 58.129
		},
		{
			"runtime": "lambda-perf-bun-128-arm64",
			"displayName": "bun (prov.al2)",
			"initDurations": [
				324.23,
				329.84,
				330.88,
				325.88,
				330.4,
				325.92,
				320.33,
				338.61,
				320.29,
				326.58
			],
			"memorySize": 128,
			"architecture": "arm64",
			"averageMemoryUsed": 69.9,
			"averageDuration": 123.138,
			"averageColdStartDuration": 327.296
		},
		{
			"runtime": "lambda-perf-dotnet6-512-x86_64",
			"displayName": "dotnet6",
			"initDurations": [
				252.91,
				259.29,
				240.81,
				227.93,
				239.46,
				233.15,
				338.61,
				224.01,
				225.59,
				227.03
			],
			"memorySize": 512,
			"architecture": "x86_64",
			"averageMemoryUsed": 59.2,
			"averageDuration": 133.183,
			"averageColdStartDuration": 246.879
		},
		{
			"runtime": "lambda-perf-nodejs16x-512-arm64",
			"displayName": "nodejs16.x",
			"initDurations": [
				158.61,
				161.81,
				162.44,
				161,
				161.16,
				152.51,
				156.43,
				160.92,
				159.07,
				228.32
			],
			"memorySize": 512,
			"architecture": "arm64",
			"averageMemoryUsed": 55,
			"averageDuration": 3.202,
			"averageColdStartDuration": 166.227
		},
		{
			"runtime": "lambda-perf-cpp11-128-arm64",
			"displayName": "c++ 11 (prov.al2)",
			"initDurations": [
				97.64,
				99.74,
				108.05,
				96.27,
				98.04,
				96.08,
				97.42,
				97.6,
				103.28,
				95.18
			],
			"memorySize": 128,
			"architecture": "arm64",
			"averageMemoryUsed": 28.5,
			"averageDuration": 1.274,
			"averageColdStartDuration": 98.93
		},
		{
			"runtime": "lambda-perf-java8_al2-1024-x86_64",
			"displayName": "java8.al2",
			"initDurations": [
				269.86,
				192.98,
				241,
				244.92,
				222.65,
				231.95,
				232.73,
				217.4,
				227.41,
				204.26
			],
			"memorySize": 1024,
			"architecture": "x86_64",
			"averageMemoryUsed": 56.8,
			"averageDuration": 4.327,
			"averageColdStartDuration": 228.516
		},
		{
			"runtime": "lambda-perf-python311-512-x86_64",
			"displayName": "python3.11",
			"initDurations": [
				133.51,
				176.36,
				121.82,
				112.17,
				116.05,
				136.14,
				142.18,
				121.46,
				410.57,
				202.41
			],
			"memorySize": 512,
			"architecture": "x86_64",
			"averageMemoryUsed": 40,
			"averageDuration": 1.942,
			"averageColdStartDuration": 167.267
		},
		{
			"runtime": "lambda-perf-nodejs18x-128-x86_64",
			"displayName": "nodejs18.x",
			"initDurations": [
				181.53,
				244.19,
				170.03,
				191.13,
				186.97,
				139.81,
				168.85,
				173.1,
				197.4,
				164.35
			],
			"memorySize": 128,
			"architecture": "x86_64",
			"averageMemoryUsed": 67,
			"averageDuration": 11.187,
			"averageColdStartDuration": 181.736
		},
		{
			"runtime": "lambda-perf-dotnet6-128-arm64",
			"displayName": "dotnet6",
			"initDurations": [
				260.38,
				275.06,
				267.98,
				263.9,
				277.36,
				262.81,
				271,
				261.98,
				271,
				259.92
			],
			"memorySize": 128,
			"architecture": "arm64",
			"averageMemoryUsed": 62.4,
			"averageDuration": 743.113,
			"averageColdStartDuration": 267.139
		},
		{
			"runtime": "lambda-perf-java8_al2-256-x86_64",
			"displayName": "java8.al2",
			"initDurations": [
				240.38,
				205.3,
				243.88,
				222.4,
				229.27,
				260.54,
				308.18,
				195.09,
				225.09,
				222.02
			],
			"memorySize": 256,
			"architecture": "x86_64",
			"averageMemoryUsed": 56.1,
			"averageDuration": 19.74,
			"averageColdStartDuration": 235.215
		},
		{
			"runtime": "lambda-perf-python39-128-arm64",
			"displayName": "python3.9",
			"initDurations": [
				107.22,
				105.4,
				108.11,
				111.97,
				103.64,
				105.76,
				110.78,
				107.89,
				116.35,
				104.89
			],
			"memorySize": 128,
			"architecture": "arm64",
			"averageMemoryUsed": 35.5,
			"averageDuration": 1.63,
			"averageColdStartDuration": 108.201
		},
		{
			"runtime": "lambda-perf-ruby27-128-x86_64",
			"displayName": "ruby2.7",
			"initDurations": [
				158.17,
				165.87,
				197.93,
				141.53,
				147.32,
				181.58,
				171.42,
				157.71,
				148.7,
				145.58
			],
			"memorySize": 128,
			"architecture": "x86_64",
			"averageMemoryUsed": 31,
			"averageDuration": 21.277,
			"averageColdStartDuration": 161.581
		},
		{
			"runtime": "lambda-perf-java8_al2-256-arm64",
			"displayName": "java8.al2",
			"initDurations": [
				265.92,
				246.1,
				247.28,
				262.49,
				253.82,
				234.66,
				251.82,
				256.46,
				241.72,
				235.91
			],
			"memorySize": 256,
			"architecture": "arm64",
			"averageMemoryUsed": 54.8,
			"averageDuration": 17.297,
			"averageColdStartDuration": 249.618
		},
		{
			"runtime": "lambda-perf-java11-1024-arm64",
			"displayName": "java11",
			"initDurations": [
				259.64,
				264.14,
				252.84,
				257,
				245.32,
				265.58,
				251.21,
				247.93,
				263.79,
				275.08
			],
			"memorySize": 1024,
			"architecture": "arm64",
			"averageMemoryUsed": 65,
			"averageDuration": 3.261,
			"averageColdStartDuration": 258.253
		},
		{
			"runtime": "lambda-perf-cpp11-256-x86_64",
			"displayName": "c++ 11 (prov.al2)",
			"initDurations": [
				129.45,
				140.6,
				120.76,
				122.75,
				120.95,
				124.56,
				132.96,
				118.21,
				115.23,
				143.95
			],
			"memorySize": 256,
			"architecture": "x86_64",
			"averageMemoryUsed": 30.5,
			"averageDuration": 1.196,
			"averageColdStartDuration": 126.942
		},
		{
			"runtime": "lambda-perf-cpp11-1024-x86_64",
			"displayName": "c++ 11 (prov.al2)",
			"initDurations": [
				125.72,
				120.65,
				120.55,
				116.57,
				124.59,
				125.36,
				125.64,
				122.94,
				144.6,
				109.15
			],
			"memorySize": 1024,
			"architecture": "x86_64",
			"averageMemoryUsed": 30,
			"averageDuration": 1.181,
			"averageColdStartDuration": 123.577
		},
		{
			"runtime": "lambda-perf-java11-512-x86_64",
			"displayName": "java11",
			"initDurations": [
				223.31,
				267.38,
				257.58,
				252.07,
				488.61,
				265.43,
				288.76,
				270.68,
				238.38,
				271.95
			],
			"memorySize": 512,
			"architecture": "x86_64",
			"averageMemoryUsed": 68.8,
			"averageDuration": 2.974,
			"averageColdStartDuration": 282.415
		},
		{
			"runtime": "lambda-perf-ruby32-256-arm64",
			"displayName": "ruby3.2",
			"initDurations": [
				205.99,
				188.76,
				195.28,
				205.88,
				193.7,
				196.34,
				184.53,
				253.81,
				192.5,
				191.66
			],
			"memorySize": 256,
			"architecture": "arm64",
			"averageMemoryUsed": 36,
			"averageDuration": 3.148,
			"averageColdStartDuration": 200.845
		},
		{
			"runtime": "lambda-perf-java8-256-x86_64",
			"displayName": "java8",
			"initDurations": [
				227.7,
				220.56,
				244.82,
				223.24,
				224.62,
				237.12,
				223.93,
				225.28,
				220.36,
				233.4
			],
			"memorySize": 256,
			"architecture": "x86_64",
			"averageMemoryUsed": 56.7,
			"averageDuration": 13.894,
			"averageColdStartDuration": 228.103
		},
		{
			"runtime": "lambda-perf-go1x-512-x86_64",
			"displayName": "go1.x",
			"initDurations": [
				85.7,
				84.78,
				91.11,
				83.46,
				103.96,
				114.98,
				86.53,
				82.73,
				83.57,
				84.68
			],
			"memorySize": 512,
			"architecture": "x86_64",
			"averageMemoryUsed": 29,
			"averageDuration": 2.252,
			"averageColdStartDuration": 90.15
		},
		{
			"runtime": "lambda-perf-java17_snapstart-512-x86_64",
			"displayName": "java17 snapstart",
			"initDurations": [
				195.63,
				216.5,
				208.62,
				246.12,
				235.24,
				243.44,
				225.7,
				203.32,
				205.04,
				201.61
			],
			"memorySize": 512,
			"architecture": "x86_64",
			"averageMemoryUsed": 67,
			"averageDuration": 2.382,
			"averageColdStartDuration": 218.122
		},
		{
			"runtime": "lambda-perf-ruby32-1024-arm64",
			"displayName": "ruby3.2",
			"initDurations": [
				200.62,
				187.81,
				201.61,
				198.65,
				203.74,
				202.84,
				196.1,
				193.77,
				197.93,
				193.93
			],
			"memorySize": 1024,
			"architecture": "arm64",
			"averageMemoryUsed": 36,
			"averageDuration": 3.16,
			"averageColdStartDuration": 197.7
		},
		{
			"runtime": "lambda-perf-ruby32-512-arm64",
			"displayName": "ruby3.2",
			"initDurations": [
				200.36,
				190.76,
				201.53,
				199.74,
				233.15,
				193.19,
				190.6,
				205.4,
				195.52,
				199.95
			],
			"memorySize": 512,
			"architecture": "arm64",
			"averageMemoryUsed": 36,
			"averageDuration": 3.272,
			"averageColdStartDuration": 201.02
		},
		{
			"runtime": "lambda-perf-graalvm_java17_on_provided_al2-1024-arm64",
			"displayName": "graalvm java17 (prov.al2)",
			"initDurations": [
				118.95,
				129.01,
				120.89,
				118.19,
				119.4,
				120.28,
				128.61,
				117.86,
				120.57,
				120.36
			],
			"memorySize": 1024,
			"architecture": "arm64",
			"averageMemoryUsed": 33.2,
			"averageDuration": 8.638,
			"averageColdStartDuration": 121.412
		},
		{
			"runtime": "lambda-perf-bun_layer-128-x86_64",
			"displayName": "bun layer(prov.al2)",
			"initDurations": [
				776.34,
				560.21,
				568.59,
				454.22,
				551.67,
				476.25,
				479.38,
				463.41,
				517.99,
				573.88
			],
			"memorySize": 128,
			"architecture": "x86_64",
			"averageMemoryUsed": 91.3,
			"averageDuration": 84.503,
			"averageColdStartDuration": 542.194
		},
		{
			"runtime": "lambda-perf-ruby32-128-arm64",
			"displayName": "ruby3.2",
			"initDurations": [
				182.44,
				256.38,
				201.32,
				195.27,
				194.96,
				199.99,
				192.53,
				197.8,
				194.09,
				194.74
			],
			"memorySize": 128,
			"architecture": "arm64",
			"averageMemoryUsed": 36,
			"averageDuration": 12.404,
			"averageColdStartDuration": 200.952
		},
		{
			"runtime": "lambda-perf-python311-256-arm64",
			"displayName": "python3.11",
			"initDurations": [
				101.64,
				103.16,
				106.59,
				106.85,
				107.99,
				103.84,
				110.74,
				119.98,
				107.99,
				115.65
			],
			"memorySize": 256,
			"architecture": "arm64",
			"averageMemoryUsed": 39,
			"averageDuration": 1.682,
			"averageColdStartDuration": 108.443
		},
		{
			"runtime": "lambda-perf-python311-128-x86_64",
			"displayName": "python3.11",
			"initDurations": [
				179.05,
				118.56,
				121.11,
				122.41,
				118.42,
				157.46,
				211.31,
				125.77,
				150.41,
				111.12
			],
			"memorySize": 128,
			"architecture": "x86_64",
			"averageMemoryUsed": 40,
			"averageDuration": 2.317,
			"averageColdStartDuration": 141.562
		},
		{
			"runtime": "lambda-perf-nodejs14x-512-x86_64",
			"displayName": "nodejs14.x",
			"initDurations": [
				183.91,
				197.37,
				193.21,
				145.92,
				182.58,
				168.62,
				182.53,
				173.53,
				174.59,
				168.74
			],
			"memorySize": 512,
			"architecture": "x86_64",
			"averageMemoryUsed": 57,
			"averageDuration": 2.64,
			"averageColdStartDuration": 177.1
		},
		{
			"runtime": "lambda-perf-graalvm_java17_on_provided_al2-256-arm64",
			"displayName": "graalvm java17 (prov.al2)",
			"initDurations": [
				118.34,
				122.01,
				122.34,
				121.14,
				118.22,
				121.57,
				121.73,
				117.72,
				119.73,
				120.35
			],
			"memorySize": 256,
			"architecture": "arm64",
			"averageMemoryUsed": 33,
			"averageDuration": 33.366,
			"averageColdStartDuration": 120.315
		},
		{
			"runtime": "lambda-perf-dotnet7_aot_on_provided_al2-512-arm64",
			"displayName": "dotnet7 aot (prov.al2)",
			"initDurations": [
				144.12,
				150.1,
				147.26,
				144.41,
				150.93,
				149.36,
				145.05,
				152.69,
				147.15,
				140.96
			],
			"memorySize": 512,
			"architecture": "arm64",
			"averageMemoryUsed": 41,
			"averageDuration": 82.107,
			"averageColdStartDuration": 147.203
		},
		{
			"runtime": "lambda-perf-dotnet7_aot_on_provided_al2-128-x86_64",
			"displayName": "dotnet7 aot (prov.al2)",
			"initDurations": [
				110.1,
				121.45,
				109.62,
				99.29,
				116.09,
				101.39,
				114.49,
				118.34,
				109.47,
				109.69
			],
			"memorySize": 128,
			"architecture": "x86_64",
			"averageMemoryUsed": 34,
			"averageDuration": 35.414,
			"averageColdStartDuration": 110.993
		},
		{
			"runtime": "lambda-perf-dotnet6-256-arm64",
			"displayName": "dotnet6",
			"initDurations": [
				257.52,
				267.15,
				261.08,
				265.79,
				262.69,
				257.27,
				268.83,
				267.61,
				272.86,
				253.47
			],
			"memorySize": 256,
			"architecture": "arm64",
			"averageMemoryUsed": 62.5,
			"averageDuration": 380.75,
			"averageColdStartDuration": 263.427
		},
		{
			"runtime": "lambda-perf-java8-512-x86_64",
			"displayName": "java8",
			"initDurations": [
				238.12,
				224.43,
				221.46,
				260.31,
				228.54,
				248.59,
				189.66,
				228.7,
				240.05,
				232.7
			],
			"memorySize": 512,
			"architecture": "x86_64",
			"averageMemoryUsed": 58,
			"averageDuration": 6.768,
			"averageColdStartDuration": 231.256
		},
		{
			"runtime": "lambda-perf-python37-128-x86_64",
			"displayName": "python3.7",
			"initDurations": [
				117.17,
				116.69,
				98.47,
				123.51,
				135.26,
				129.39,
				118.78,
				122.13,
				111.08,
				112.59
			],
			"memorySize": 128,
			"architecture": "x86_64",
			"averageMemoryUsed": 36,
			"averageDuration": 2.284,
			"averageColdStartDuration": 118.507
		},
		{
			"runtime": "lambda-perf-dotnet6-1024-x86_64",
			"displayName": "dotnet6",
			"initDurations": [
				250.36,
				246.34,
				225.98,
				224.1,
				235.49,
				257.96,
				266.66,
				246.05,
				232.35,
				243.45
			],
			"memorySize": 1024,
			"architecture": "x86_64",
			"averageMemoryUsed": 59.1,
			"averageDuration": 55.469,
			"averageColdStartDuration": 242.874
		},
		{
			"runtime": "lambda-perf-go_on_provided_al2-128-x86_64",
			"displayName": "go (prov.al2)",
			"initDurations": [
				67.91,
				54.84,
				58.69,
				54.91,
				56.55,
				121.52,
				55.36,
				59.59,
				53.65,
				53.98
			],
			"memorySize": 128,
			"architecture": "x86_64",
			"averageMemoryUsed": 19.3,
			"averageDuration": 1.426,
			"averageColdStartDuration": 63.7
		},
		{
			"runtime": "lambda-perf-rust_on_provided_al2-512-x86_64",
			"displayName": "rust (prov.al2)",
			"initDurations": [
				20.35,
				17.08,
				18.27,
				15.84,
				14.18,
				14.74,
				17.18,
				16.45,
				15.05,
				20.43
			],
			"memorySize": 512,
			"architecture": "x86_64",
			"averageMemoryUsed": 14,
			"averageDuration": 1.198,
			"averageColdStartDuration": 16.957
		},
		{
			"runtime": "lambda-perf-go1x-1024-x86_64",
			"displayName": "go1.x",
			"initDurations": [
				72.27,
				84.32,
				86.87,
				89.05,
				84.35,
				84.51,
				84.08,
				85.65,
				88.35,
				85.16
			],
			"memorySize": 1024,
			"architecture": "x86_64",
			"averageMemoryUsed": 29.1,
			"averageDuration": 2.164,
			"averageColdStartDuration": 84.461
		},
		{
			"runtime": "lambda-perf-dotnet6-512-arm64",
			"displayName": "dotnet6",
			"initDurations": [
				322.78,
				275.57,
				282.73,
				255.75,
				255.51,
				263.07,
				264.25,
				268.87,
				257.33,
				249.72
			],
			"memorySize": 512,
			"architecture": "arm64",
			"averageMemoryUsed": 62.7,
			"averageDuration": 171.452,
			"averageColdStartDuration": 269.558
		},
		{
			"runtime": "lambda-perf-go_on_provided_al2-1024-x86_64",
			"displayName": "go (prov.al2)",
			"initDurations": [
				59.86,
				53.16,
				59.93,
				58.78,
				54.4,
				53.01,
				54.23,
				54.32,
				56.28,
				66.5
			],
			"memorySize": 1024,
			"architecture": "x86_64",
			"averageMemoryUsed": 19.2,
			"averageDuration": 1.481,
			"averageColdStartDuration": 57.047
		},
		{
			"runtime": "lambda-perf-nodejs18x-512-x86_64",
			"displayName": "nodejs18.x",
			"initDurations": [
				173.69,
				176,
				185.45,
				171.39,
				170,
				229.17,
				181.4,
				176.43,
				206.75,
				171.1
			],
			"memorySize": 512,
			"architecture": "x86_64",
			"averageMemoryUsed": 67,
			"averageDuration": 3.462,
			"averageColdStartDuration": 184.138
		},
		{
			"runtime": "lambda-perf-ruby32-128-x86_64",
			"displayName": "ruby3.2",
			"initDurations": [
				181.27,
				192.1,
				432.55,
				220.52,
				182.92,
				223.38,
				201.25,
				197.39,
				176.45,
				211.4
			],
			"memorySize": 128,
			"architecture": "x86_64",
			"averageMemoryUsed": 36,
			"averageDuration": 11.396,
			"averageColdStartDuration": 221.923
		},
		{
			"runtime": "lambda-perf-python310-128-arm64",
			"displayName": "python3.10",
			"initDurations": [
				113.37,
				104.17,
				99.92,
				107.99,
				108.61,
				117.09,
				107.26,
				105.45,
				103.42,
				152.17
			],
			"memorySize": 128,
			"architecture": "arm64",
			"averageMemoryUsed": 35.9,
			"averageDuration": 1.694,
			"averageColdStartDuration": 111.945
		},
		{
			"runtime": "lambda-perf-nodejs16x-256-x86_64",
			"displayName": "nodejs16.x",
			"initDurations": [
				156.94,
				142.46,
				158.67,
				158.5,
				164.78,
				120.65,
				159.49,
				153.35,
				161.74,
				151.58
			],
			"memorySize": 256,
			"architecture": "x86_64",
			"averageMemoryUsed": 57.1,
			"averageDuration": 3.9,
			"averageColdStartDuration": 152.816
		},
		{
			"runtime": "lambda-perf-python37-256-x86_64",
			"displayName": "python3.7",
			"initDurations": [
				123.37,
				128.54,
				136.66,
				197.08,
				111.72,
				115.11,
				164.55,
				149.07,
				114.13,
				119.96
			],
			"memorySize": 256,
			"architecture": "x86_64",
			"averageMemoryUsed": 36,
			"averageDuration": 2.005,
			"averageColdStartDuration": 136.019
		},
		{
			"runtime": "lambda-perf-cpp11-1024-arm64",
			"displayName": "c++ 11 (prov.al2)",
			"initDurations": [
				99.86,
				100.18,
				99.03,
				97.95,
				96.83,
				95.2,
				94.22,
				100.5,
				99.5,
				94.44
			],
			"memorySize": 1024,
			"architecture": "arm64",
			"averageMemoryUsed": 28.6,
			"averageDuration": 1.311,
			"averageColdStartDuration": 97.771
		},
		{
			"runtime": "lambda-perf-quarkus_native_on_provided_al2-256-x86_64",
			"displayName": "quarkus (prov.al2)",
			"initDurations": [
				259.08,
				261.27,
				269.9,
				258.72,
				257.19,
				295.36,
				261.13,
				257.16,
				261.91,
				278.19
			],
			"memorySize": 256,
			"architecture": "x86_64",
			"averageMemoryUsed": 57.3,
			"averageDuration": 101.311,
			"averageColdStartDuration": 265.991
		},
		{
			"runtime": "lambda-perf-go_on_provided_al2-256-arm64",
			"displayName": "go (prov.al2)",
			"initDurations": [
				47.71,
				48.36,
				48.22,
				47.95,
				47.81,
				48.89,
				48.6,
				49.24,
				47.87,
				47.76
			],
			"memorySize": 256,
			"architecture": "arm64",
			"averageMemoryUsed": 18.6,
			"averageDuration": 1.583,
			"averageColdStartDuration": 48.241
		},
		{
			"runtime": "lambda-perf-python39-512-arm64",
			"displayName": "python3.9",
			"initDurations": [
				110.52,
				108.04,
				101.7,
				113.99,
				107.91,
				114.26,
				112.05,
				111.13,
				107.41,
				142.59
			],
			"memorySize": 512,
			"architecture": "arm64",
			"averageMemoryUsed": 35.3,
			"averageDuration": 1.701,
			"averageColdStartDuration": 112.96
		},
		{
			"runtime": "lambda-perf-java17-1024-x86_64",
			"displayName": "java17",
			"initDurations": [
				194.1,
				218.41,
				218.31,
				204.2,
				208.65,
				214.6,
				228.98,
				212.1,
				205.06,
				239.49
			],
			"memorySize": 1024,
			"architecture": "x86_64",
			"averageMemoryUsed": 67.2,
			"averageDuration": 3.762,
			"averageColdStartDuration": 214.39
		},
		{
			"runtime": "lambda-perf-python39-256-arm64",
			"displayName": "python3.9",
			"initDurations": [
				113.43,
				111.64,
				109.68,
				109.26,
				106.16,
				113.84,
				110.14,
				100.6,
				117.27,
				109.98
			],
			"memorySize": 256,
			"architecture": "arm64",
			"averageMemoryUsed": 35.2,
			"averageDuration": 1.609,
			"averageColdStartDuration": 110.2
		},
		{
			"runtime": "lambda-perf-nodejs16x-1024-x86_64",
			"displayName": "nodejs16.x",
			"initDurations": [
				160.93,
				157.9,
				158.43,
				147.85,
				151.01,
				158.4,
				160.51,
				162.04,
				172.15,
				149.63
			],
			"memorySize": 1024,
			"architecture": "x86_64",
			"averageMemoryUsed": 57.1,
			"averageDuration": 2.688,
			"averageColdStartDuration": 157.885
		},
		{
			"runtime": "lambda-perf-dotnet7_aot_on_provided_al2-256-arm64",
			"displayName": "dotnet7 aot (prov.al2)",
			"initDurations": [
				141.95,
				163.21,
				144.71,
				146.34,
				146.06,
				142.9,
				146.24,
				163.97,
				137.66,
				146.04
			],
			"memorySize": 256,
			"architecture": "arm64",
			"averageMemoryUsed": 41.2,
			"averageDuration": 183.065,
			"averageColdStartDuration": 147.908
		},
		{
			"runtime": "lambda-perf-quarkus_native_on_provided_al2-128-x86_64",
			"displayName": "quarkus (prov.al2)",
			"initDurations": [
				262.35,
				262.3,
				254.61,
				258.14,
				260.2,
				236.56,
				267.92,
				280.31,
				255.96,
				266.46
			],
			"memorySize": 128,
			"architecture": "x86_64",
			"averageMemoryUsed": 57.2,
			"averageDuration": 221.01,
			"averageColdStartDuration": 260.481
		},
		{
			"runtime": "lambda-perf-python310-256-arm64",
			"displayName": "python3.10",
			"initDurations": [
				104.02,
				107.86,
				113.43,
				108.81,
				103.08,
				107.6,
				113.84,
				113.02,
				106.66,
				110.56
			],
			"memorySize": 256,
			"architecture": "arm64",
			"averageMemoryUsed": 35.9,
			"averageDuration": 1.667,
			"averageColdStartDuration": 108.888
		},
		{
			"runtime": "lambda-perf-rust_on_provided_al2-128-x86_64",
			"displayName": "rust (prov.al2)",
			"initDurations": [
				58.02,
				16.74,
				61.08,
				15.16,
				16.77,
				15.83,
				15.17,
				14.46,
				15.72,
				16.59
			],
			"memorySize": 128,
			"architecture": "x86_64",
			"averageMemoryUsed": 14,
			"averageDuration": 1.667,
			"averageColdStartDuration": 24.554
		},
		{
			"runtime": "lambda-perf-graalvm_java17_on_provided_al2-512-arm64",
			"displayName": "graalvm java17 (prov.al2)",
			"initDurations": [
				118.53,
				118.85,
				116.38,
				119.62,
				118.75,
				119.03,
				118.72,
				121.06,
				122.61,
				137.16
			],
			"memorySize": 512,
			"architecture": "arm64",
			"averageMemoryUsed": 33.1,
			"averageDuration": 15.098,
			"averageColdStartDuration": 121.071
		},
		{
			"runtime": "lambda-perf-go_on_provided_al2-128-arm64",
			"displayName": "go (prov.al2)",
			"initDurations": [
				51.34,
				47.42,
				49.91,
				47.77,
				47.48,
				50.11,
				47.59,
				47.13,
				48.27,
				47.27
			],
			"memorySize": 128,
			"architecture": "arm64",
			"averageMemoryUsed": 18.8,
			"averageDuration": 1.448,
			"averageColdStartDuration": 48.429
		},
		{
			"runtime": "lambda-perf-nodejs14x-1024-arm64",
			"displayName": "nodejs14.x",
			"initDurations": [
				179.08,
				177.63,
				176.97,
				185.29,
				181.78,
				181.31,
				194.55,
				175.22,
				187.81,
				177.06
			],
			"memorySize": 1024,
			"architecture": "arm64",
			"averageMemoryUsed": 56,
			"averageDuration": 3.304,
			"averageColdStartDuration": 181.67
		},
		{
			"runtime": "lambda-perf-java11-256-x86_64",
			"displayName": "java11",
			"initDurations": [
				265.27,
				269.15,
				279.36,
				259.35,
				327.49,
				252.98,
				298.12,
				278.98,
				265.16,
				268.55
			],
			"memorySize": 256,
			"architecture": "x86_64",
			"averageMemoryUsed": 69.1,
			"averageDuration": 3.467,
			"averageColdStartDuration": 276.441
		},
		{
			"runtime": "lambda-perf-java17-256-x86_64",
			"displayName": "java17",
			"initDurations": [
				204.86,
				202.7,
				267.99,
				206.86,
				269.36,
				243.04,
				234.43,
				174.5,
				190.42,
				185.92
			],
			"memorySize": 256,
			"architecture": "x86_64",
			"averageMemoryUsed": 67.3,
			"averageDuration": 2.174,
			"averageColdStartDuration": 218.008
		},
		{
			"runtime": "lambda-perf-java17-128-x86_64",
			"displayName": "java17",
			"initDurations": [
				246.5,
				213.25,
				213.15,
				198.04,
				216.68,
				216.59,
				249.49,
				209.5,
				184.44,
				218.86
			],
			"memorySize": 128,
			"architecture": "x86_64",
			"averageMemoryUsed": 67.4,
			"averageDuration": 8.829,
			"averageColdStartDuration": 216.65
		},
		{
			"runtime": "lambda-perf-nodejs14x-256-arm64",
			"displayName": "nodejs14.x",
			"initDurations": [
				178.81,
				188.08,
				183.37,
				177.73,
				176.3,
				173.22,
				181.72,
				180.32,
				187.64,
				186.68
			],
			"memorySize": 256,
			"architecture": "arm64",
			"averageMemoryUsed": 56,
			"averageDuration": 3.232,
			"averageColdStartDuration": 181.387
		},
		{
			"runtime": "lambda-perf-python37-1024-x86_64",
			"displayName": "python3.7",
			"initDurations": [
				115.74,
				122.11,
				120.12,
				100.37,
				143.93,
				108.35,
				156.51,
				127.57,
				124.13,
				112.93
			],
			"memorySize": 1024,
			"architecture": "x86_64",
			"averageMemoryUsed": 36,
			"averageDuration": 2.03,
			"averageColdStartDuration": 123.176
		},
		{
			"runtime": "lambda-perf-python38-1024-x86_64",
			"displayName": "python3.8",
			"initDurations": [
				135.22,
				119,
				119.64,
				121.23,
				193.62,
				155.14,
				119.14,
				137.68,
				125.3,
				141.06
			],
			"memorySize": 1024,
			"architecture": "x86_64",
			"averageMemoryUsed": 38.4,
			"averageDuration": 3.96,
			"averageColdStartDuration": 136.703
		},
		{
			"runtime": "lambda-perf-swift58-256-arm64",
			"displayName": "apple swift 5.8 (prov.al2)",
			"initDurations": [
				113.96,
				107,
				112.61,
				109.72,
				110.13,
				112.26,
				109.98,
				108.61,
				106.7,
				109.83
			],
			"memorySize": 256,
			"architecture": "arm64",
			"averageMemoryUsed": 31,
			"averageDuration": 1.61,
			"averageColdStartDuration": 110.08
		},
		{
			"runtime": "lambda-perf-rust_on_provided_al2-512-arm64",
			"displayName": "rust (prov.al2)",
			"initDurations": [
				15.35,
				13.86,
				14.55,
				15.09,
				14.14,
				14.6,
				14.56,
				13.13,
				14.77,
				13.3
			],
			"memorySize": 512,
			"architecture": "arm64",
			"averageMemoryUsed": 14,
			"averageDuration": 1.357,
			"averageColdStartDuration": 14.335
		},
		{
			"runtime": "lambda-perf-ruby32-1024-x86_64",
			"displayName": "ruby3.2",
			"initDurations": [
				230.09,
				358.08,
				187.21,
				222.32,
				189.05,
				253.18,
				191.62,
				220.46,
				191.45,
				214.44
			],
			"memorySize": 1024,
			"architecture": "x86_64",
			"averageMemoryUsed": 36.1,
			"averageDuration": 2.915,
			"averageColdStartDuration": 225.79
		},
		{
			"runtime": "lambda-perf-bun_layer-1024-x86_64",
			"displayName": "bun layer(prov.al2)",
			"initDurations": [
				809.42,
				610.86,
				482.95,
				552.54,
				420.69,
				497.64,
				520.66,
				801.65,
				525.22,
				820.07
			],
			"memorySize": 1024,
			"architecture": "x86_64",
			"averageMemoryUsed": 93.4,
			"averageDuration": 7.397,
			"averageColdStartDuration": 604.17
		},
		{
			"runtime": "lambda-perf-java17-512-arm64",
			"displayName": "java17",
			"initDurations": [
				223.34,
				249.12,
				220.33,
				227.79,
				232.68,
				219.79,
				221.38,
				220.29,
				233.31,
				218.05
			],
			"memorySize": 512,
			"architecture": "arm64",
			"averageMemoryUsed": 66,
			"averageDuration": 2.594,
			"averageColdStartDuration": 226.608
		},
		{
			"runtime": "lambda-perf-go_on_provided-512-x86_64",
			"displayName": "go (provided)",
			"initDurations": [
				55.29,
				57.76,
				52.68,
				55.93,
				60.32,
				54.05,
				52.76,
				57.54,
				55.1,
				57.15
			],
			"memorySize": 512,
			"architecture": "x86_64",
			"averageMemoryUsed": 19,
			"averageDuration": 1.605,
			"averageColdStartDuration": 55.858
		},
		{
			"runtime": "lambda-perf-nodejs16x-128-x86_64",
			"displayName": "nodejs16.x",
			"initDurations": [
				153.66,
				152.67,
				153.95,
				125.95,
				156.88,
				152.65,
				154.46,
				145.81,
				167.24,
				190.81
			],
			"memorySize": 128,
			"architecture": "x86_64",
			"averageMemoryUsed": 57.1,
			"averageDuration": 15.327,
			"averageColdStartDuration": 155.408
		},
		{
			"runtime": "lambda-perf-graalvm_java17_on_provided_al2-1024-x86_64",
			"displayName": "graalvm java17 (prov.al2)",
			"initDurations": [
				128.8,
				116.02,
				114.95,
				128.63,
				130.8,
				117.37,
				110.04,
				111.16,
				132.19,
				176.68
			],
			"memorySize": 1024,
			"architecture": "x86_64",
			"averageMemoryUsed": 34,
			"averageDuration": 8.807,
			"averageColdStartDuration": 126.664
		},
		{
			"runtime": "lambda-perf-rust_on_provided_al2-256-arm64",
			"displayName": "rust (prov.al2)",
			"initDurations": [
				14.01,
				15.11,
				14.86,
				14.22,
				14.86,
				15.23,
				14.34,
				14.63,
				14.48,
				13.42
			],
			"memorySize": 256,
			"architecture": "arm64",
			"averageMemoryUsed": 14,
			"averageDuration": 1.402,
			"averageColdStartDuration": 14.516
		},
		{
			"runtime": "lambda-perf-nodejs18x-256-arm64",
			"displayName": "nodejs18.x",
			"initDurations": [
				177.81,
				173.06,
				162.93,
				166.27,
				170.22,
				170.05,
				178.64,
				175.95,
				165.54,
				174.99
			],
			"memorySize": 256,
			"architecture": "arm64",
			"averageMemoryUsed": 66,
			"averageDuration": 5.829,
			"averageColdStartDuration": 171.546
		},
		{
			"runtime": "lambda-perf-ruby32-512-x86_64",
			"displayName": "ruby3.2",
			"initDurations": [
				245.97,
				191.24,
				199.52,
				189.09,
				227.9,
				276.73,
				188.95,
				297.22,
				179.32,
				257.45
			],
			"memorySize": 512,
			"architecture": "x86_64",
			"averageMemoryUsed": 36.1,
			"averageDuration": 3.542,
			"averageColdStartDuration": 225.339
		},
		{
			"runtime": "lambda-perf-graalvm_java17_on_provided_al2-256-x86_64",
			"displayName": "graalvm java17 (prov.al2)",
			"initDurations": [
				132.83,
				138.98,
				135.29,
				126.61,
				137.49,
				126.56,
				127,
				124.46,
				125.04,
				136.25
			],
			"memorySize": 256,
			"architecture": "x86_64",
			"averageMemoryUsed": 34,
			"averageDuration": 38.652,
			"averageColdStartDuration": 131.051
		},
		{
			"runtime": "lambda-perf-dotnet6-1024-arm64",
			"displayName": "dotnet6",
			"initDurations": [
				270.98,
				245.91,
				286.21,
				271.48,
				272.6,
				257.86,
				261.37,
				267.68,
				256.83,
				266.98
			],
			"memorySize": 1024,
			"architecture": "arm64",
			"averageMemoryUsed": 62.2,
			"averageDuration": 77.022,
			"averageColdStartDuration": 265.79
		},
		{
			"runtime": "lambda-perf-java11-128-arm64",
			"displayName": "java11",
			"initDurations": [
				266.02,
				255.8,
				281.11,
				271.34,
				262.24,
				267.09,
				261.61,
				266.73,
				268.42,
				253.61
			],
			"memorySize": 128,
			"architecture": "arm64",
			"averageMemoryUsed": 66,
			"averageDuration": 8.622,
			"averageColdStartDuration": 265.397
		},
		{
			"runtime": "lambda-perf-swift58-1024-x86_64",
			"displayName": "apple swift 5.8 (prov.al2)",
			"initDurations": [
				141.09,
				123.27,
				128.66,
				102.82,
				123.18,
				121.31,
				135.38,
				106.85,
				158.47,
				117.87
			],
			"memorySize": 1024,
			"architecture": "x86_64",
			"averageMemoryUsed": 32,
			"averageDuration": 1.546,
			"averageColdStartDuration": 125.89
		},
		{
			"runtime": "lambda-perf-cpp11-512-arm64",
			"displayName": "c++ 11 (prov.al2)",
			"initDurations": [
				95.57,
				99.25,
				96.04,
				95.98,
				95.1,
				96.42,
				99.2,
				99.04,
				97.65,
				97.15
			],
			"memorySize": 512,
			"architecture": "arm64",
			"averageMemoryUsed": 28.7,
			"averageDuration": 1.36,
			"averageColdStartDuration": 97.14
		},
		{
			"runtime": "lambda-perf-ruby27-256-arm64",
			"displayName": "ruby2.7",
			"initDurations": [
				157.11,
				157.68,
				158.2,
				151.37,
				162.3,
				210.02,
				152.77,
				154.63,
				161.75,
				150.74
			],
			"memorySize": 256,
			"architecture": "arm64",
			"averageMemoryUsed": 31,
			"averageDuration": 8.35,
			"averageColdStartDuration": 161.657
		},
		{
			"runtime": "lambda-perf-java17_snapstart-128-x86_64",
			"displayName": "java17 snapstart",
			"initDurations": [
				212.29,
				201.34,
				221.61,
				235.58,
				198.74,
				200,
				263.57,
				287.39,
				198.05,
				206.82
			],
			"memorySize": 128,
			"architecture": "x86_64",
			"averageMemoryUsed": 67.3,
			"averageDuration": 8.301,
			"averageColdStartDuration": 222.539
		},
		{
			"runtime": "lambda-perf-dotnet7_aot_on_provided_al2-1024-x86_64",
			"displayName": "dotnet7 aot (prov.al2)",
			"initDurations": [
				110.78,
				102.97,
				139.49,
				112.88,
				114.78,
				107.72,
				104.02,
				112.08,
				135.15,
				113.71
			],
			"memorySize": 1024,
			"architecture": "x86_64",
			"averageMemoryUsed": 34,
			"averageDuration": 10.776,
			"averageColdStartDuration": 115.358
		},
		{
			"runtime": "lambda-perf-ruby27-1024-x86_64",
			"displayName": "ruby2.7",
			"initDurations": [
				146.41,
				133.11,
				157.97,
				141.64,
				144.06,
				157.78,
				132.42,
				145.25,
				159.8,
				153.41
			],
			"memorySize": 1024,
			"architecture": "x86_64",
			"averageMemoryUsed": 31,
			"averageDuration": 3.914,
			"averageColdStartDuration": 147.185
		},
		{
			"runtime": "lambda-perf-python311-1024-x86_64",
			"displayName": "python3.11",
			"initDurations": [
				145.13,
				116.71,
				115.04,
				115.95,
				113.49,
				123.76,
				117.03,
				119.71,
				113.56,
				168.23
			],
			"memorySize": 1024,
			"architecture": "x86_64",
			"averageMemoryUsed": 40,
			"averageDuration": 1.557,
			"averageColdStartDuration": 124.861
		},
		{
			"runtime": "lambda-perf-java8_al2-128-arm64",
			"displayName": "java8.al2",
			"initDurations": [
				236.66,
				238.87,
				227.97,
				220.98,
				248.55,
				261.52,
				239.96,
				228.91,
				270.33,
				271.56
			],
			"memorySize": 128,
			"architecture": "arm64",
			"averageMemoryUsed": 54.8,
			"averageDuration": 51.578,
			"averageColdStartDuration": 244.531
		},
		{
			"runtime": "lambda-perf-swift58-128-arm64",
			"displayName": "apple swift 5.8 (prov.al2)",
			"initDurations": [
				105.87,
				107.56,
				111.37,
				18.34,
				113.99,
				112.74,
				109.88,
				108.69,
				112.76,
				126.32
			],
			"memorySize": 128,
			"architecture": "arm64",
			"averageMemoryUsed": 29.4,
			"averageDuration": 1.503,
			"averageColdStartDuration": 102.752
		},
		{
			"runtime": "lambda-perf-bun-256-x86_64",
			"displayName": "bun (prov.al2)",
			"initDurations": [
				411.79,
				432.84,
				409.51,
				462.27,
				386.68,
				393.2,
				378.26,
				489.87,
				472.53,
				378.7
			],
			"memorySize": 256,
			"architecture": "x86_64",
			"averageMemoryUsed": 76.1,
			"averageDuration": 70.204,
			"averageColdStartDuration": 421.565
		}
	]
}